{"results":[{"alternatives":[{"transcript":"So the next topic will discuss will be how to assign easier to remember names so that we do not have to remember IP addresses. When we want to talk to a particular Oster node on a network or on the internet. In particular said that principal system that enables us to do. This is called DNS for the domain name system. What it allows us to do is work with names in place of the numerical IP addresses that the actual underlined protocols. Like the IP protocol will depend upon its also set up in a hierarchical way for scalability and a variety of other reasons so that we can reasonably refer to these names. And then also what address is and servers would be corresponding to them. It also incorporates cashing so that we have mappings from","confidence":0.967787504196167,"words":[{"startTime":{"nanos":300000000},"endTime":{"nanos":800000000},"word":"So"},{"startTime":{"nanos":800000000},"endTime":{"nanos":800000000},"word":"the"},{"startTime":{"nanos":800000000},"endTime":{"seconds":"1"},"word":"next"},{"startTime":{"seconds":"1"},"endTime":{"seconds":"1","nanos":400000000},"word":"topic"},{"startTime":{"seconds":"1","nanos":400000000},"endTime":{"seconds":"1","nanos":600000000},"word":"will"},{"startTime":{"seconds":"1","nanos":600000000},"endTime":{"seconds":"2","nanos":100000000},"word":"discuss"},{"startTime":{"seconds":"2","nanos":100000000},"endTime":{"seconds":"2","nanos":500000000},"word":"will"},{"startTime":{"seconds":"2","nanos":500000000},"endTime":{"seconds":"2","nanos":700000000},"word":"be"},{"startTime":{"seconds":"2","nanos":700000000},"endTime":{"seconds":"3","nanos":900000000},"word":"how"},{"startTime":{"seconds":"3","nanos":900000000},"endTime":{"seconds":"4","nanos":300000000},"word":"to"},{"startTime":{"seconds":"4","nanos":300000000},"endTime":{"seconds":"4","nanos":800000000},"word":"assign"},{"startTime":{"seconds":"4","nanos":800000000},"endTime":{"seconds":"5","nanos":200000000},"word":"easier"},{"startTime":{"seconds":"5","nanos":200000000},"endTime":{"seconds":"5","nanos":300000000},"word":"to"},{"startTime":{"seconds":"5","nanos":300000000},"endTime":{"seconds":"5","nanos":400000000},"word":"remember"},{"startTime":{"seconds":"5","nanos":400000000},"endTime":{"seconds":"5","nanos":800000000},"word":"names"},{"startTime":{"seconds":"5","nanos":800000000},"endTime":{"seconds":"6","nanos":900000000},"word":"so"},{"startTime":{"seconds":"6","nanos":900000000},"endTime":{"seconds":"7"},"word":"that"},{"startTime":{"seconds":"7"},"endTime":{"seconds":"7","nanos":300000000},"word":"we"},{"startTime":{"seconds":"7","nanos":300000000},"endTime":{"seconds":"7","nanos":600000000},"word":"do"},{"startTime":{"seconds":"7","nanos":600000000},"endTime":{"seconds":"7","nanos":700000000},"word":"not"},{"startTime":{"seconds":"7","nanos":700000000},"endTime":{"seconds":"8","nanos":200000000},"word":"have"},{"startTime":{"seconds":"8","nanos":200000000},"endTime":{"seconds":"8","nanos":600000000},"word":"to"},{"startTime":{"seconds":"8","nanos":600000000},"endTime":{"seconds":"9"},"word":"remember"},{"startTime":{"seconds":"9"},"endTime":{"seconds":"9","nanos":500000000},"word":"IP"},{"startTime":{"seconds":"9","nanos":500000000},"endTime":{"seconds":"10","nanos":200000000},"word":"addresses."},{"startTime":{"seconds":"10","nanos":200000000},"endTime":{"seconds":"10","nanos":400000000},"word":"When"},{"startTime":{"seconds":"10","nanos":400000000},"endTime":{"seconds":"10","nanos":500000000},"word":"we"},{"startTime":{"seconds":"10","nanos":500000000},"endTime":{"seconds":"10","nanos":700000000},"word":"want"},{"startTime":{"seconds":"10","nanos":700000000},"endTime":{"seconds":"10","nanos":800000000},"word":"to"},{"startTime":{"seconds":"10","nanos":800000000},"endTime":{"seconds":"11"},"word":"talk"},{"startTime":{"seconds":"11"},"endTime":{"seconds":"11","nanos":300000000},"word":"to"},{"startTime":{"seconds":"11","nanos":300000000},"endTime":{"seconds":"11","nanos":400000000},"word":"a"},{"startTime":{"seconds":"11","nanos":400000000},"endTime":{"seconds":"11","nanos":800000000},"word":"particular"},{"startTime":{"seconds":"11","nanos":800000000},"endTime":{"seconds":"13"},"word":"Oster"},{"startTime":{"seconds":"13"},"endTime":{"seconds":"13","nanos":500000000},"word":"node"},{"startTime":{"seconds":"13","nanos":500000000},"endTime":{"seconds":"14","nanos":100000000},"word":"on"},{"startTime":{"seconds":"14","nanos":100000000},"endTime":{"seconds":"14","nanos":200000000},"word":"a"},{"startTime":{"seconds":"14","nanos":200000000},"endTime":{"seconds":"14","nanos":500000000},"word":"network"},{"startTime":{"seconds":"14","nanos":500000000},"endTime":{"seconds":"14","nanos":700000000},"word":"or"},{"startTime":{"seconds":"14","nanos":700000000},"endTime":{"seconds":"14","nanos":800000000},"word":"on"},{"startTime":{"seconds":"14","nanos":800000000},"endTime":{"seconds":"14","nanos":900000000},"word":"the"},{"startTime":{"seconds":"14","nanos":900000000},"endTime":{"seconds":"15","nanos":400000000},"word":"internet."},{"startTime":{"seconds":"15","nanos":400000000},"endTime":{"seconds":"15","nanos":900000000},"word":"In"},{"startTime":{"seconds":"15","nanos":900000000},"endTime":{"seconds":"16","nanos":500000000},"word":"particular"},{"startTime":{"seconds":"16","nanos":500000000},"endTime":{"seconds":"19","nanos":100000000},"word":"said"},{"startTime":{"seconds":"19","nanos":100000000},"endTime":{"seconds":"19","nanos":300000000},"word":"that"},{"startTime":{"seconds":"19","nanos":300000000},"endTime":{"seconds":"19","nanos":700000000},"word":"principal"},{"startTime":{"seconds":"19","nanos":700000000},"endTime":{"seconds":"20","nanos":500000000},"word":"system"},{"startTime":{"seconds":"20","nanos":500000000},"endTime":{"seconds":"21","nanos":300000000},"word":"that"},{"startTime":{"seconds":"21","nanos":300000000},"endTime":{"seconds":"21","nanos":900000000},"word":"enables"},{"startTime":{"seconds":"21","nanos":900000000},"endTime":{"seconds":"22","nanos":200000000},"word":"us"},{"startTime":{"seconds":"22","nanos":200000000},"endTime":{"seconds":"22","nanos":400000000},"word":"to"},{"startTime":{"seconds":"22","nanos":400000000},"endTime":{"seconds":"22","nanos":600000000},"word":"do."},{"startTime":{"seconds":"22","nanos":600000000},"endTime":{"seconds":"22","nanos":800000000},"word":"This"},{"startTime":{"seconds":"22","nanos":800000000},"endTime":{"seconds":"23","nanos":100000000},"word":"is"},{"startTime":{"seconds":"23","nanos":100000000},"endTime":{"seconds":"23","nanos":300000000},"word":"called"},{"startTime":{"seconds":"23","nanos":300000000},"endTime":{"seconds":"23","nanos":800000000},"word":"DNS"},{"startTime":{"seconds":"23","nanos":800000000},"endTime":{"seconds":"24"},"word":"for"},{"startTime":{"seconds":"24"},"endTime":{"seconds":"24","nanos":100000000},"word":"the"},{"startTime":{"seconds":"24","nanos":100000000},"endTime":{"seconds":"24","nanos":500000000},"word":"domain"},{"startTime":{"seconds":"24","nanos":500000000},"endTime":{"seconds":"24","nanos":600000000},"word":"name"},{"startTime":{"seconds":"24","nanos":600000000},"endTime":{"seconds":"24","nanos":900000000},"word":"system."},{"startTime":{"seconds":"24","nanos":900000000},"endTime":{"seconds":"26","nanos":200000000},"word":"What"},{"startTime":{"seconds":"26","nanos":200000000},"endTime":{"seconds":"26","nanos":300000000},"word":"it"},{"startTime":{"seconds":"26","nanos":300000000},"endTime":{"seconds":"26","nanos":600000000},"word":"allows"},{"startTime":{"seconds":"26","nanos":600000000},"endTime":{"seconds":"26","nanos":600000000},"word":"us"},{"startTime":{"seconds":"26","nanos":600000000},"endTime":{"seconds":"26","nanos":800000000},"word":"to"},{"startTime":{"seconds":"26","nanos":800000000},"endTime":{"seconds":"27","nanos":100000000},"word":"do"},{"startTime":{"seconds":"27","nanos":100000000},"endTime":{"seconds":"27","nanos":300000000},"word":"is"},{"startTime":{"seconds":"27","nanos":300000000},"endTime":{"seconds":"27","nanos":600000000},"word":"work"},{"startTime":{"seconds":"27","nanos":600000000},"endTime":{"seconds":"27","nanos":700000000},"word":"with"},{"startTime":{"seconds":"27","nanos":700000000},"endTime":{"seconds":"28","nanos":300000000},"word":"names"},{"startTime":{"seconds":"28","nanos":300000000},"endTime":{"seconds":"28","nanos":600000000},"word":"in"},{"startTime":{"seconds":"28","nanos":600000000},"endTime":{"seconds":"28","nanos":900000000},"word":"place"},{"startTime":{"seconds":"28","nanos":900000000},"endTime":{"seconds":"29","nanos":200000000},"word":"of"},{"startTime":{"seconds":"29","nanos":200000000},"endTime":{"seconds":"29","nanos":400000000},"word":"the"},{"startTime":{"seconds":"29","nanos":400000000},"endTime":{"seconds":"30","nanos":500000000},"word":"numerical"},{"startTime":{"seconds":"30","nanos":500000000},"endTime":{"seconds":"31","nanos":200000000},"word":"IP"},{"startTime":{"seconds":"31","nanos":200000000},"endTime":{"seconds":"31","nanos":600000000},"word":"addresses"},{"startTime":{"seconds":"31","nanos":600000000},"endTime":{"seconds":"32","nanos":100000000},"word":"that"},{"startTime":{"seconds":"32","nanos":100000000},"endTime":{"seconds":"32","nanos":300000000},"word":"the"},{"startTime":{"seconds":"32","nanos":300000000},"endTime":{"seconds":"32","nanos":600000000},"word":"actual"},{"startTime":{"seconds":"32","nanos":600000000},"endTime":{"seconds":"33","nanos":800000000},"word":"underlined"},{"startTime":{"seconds":"33","nanos":800000000},"endTime":{"seconds":"34","nanos":400000000},"word":"protocols."},{"startTime":{"seconds":"34","nanos":400000000},"endTime":{"seconds":"34","nanos":700000000},"word":"Like"},{"startTime":{"seconds":"34","nanos":700000000},"endTime":{"seconds":"35","nanos":400000000},"word":"the"},{"startTime":{"seconds":"35","nanos":400000000},"endTime":{"seconds":"35","nanos":700000000},"word":"IP"},{"startTime":{"seconds":"35","nanos":700000000},"endTime":{"seconds":"36"},"word":"protocol"},{"startTime":{"seconds":"36"},"endTime":{"seconds":"36","nanos":400000000},"word":"will"},{"startTime":{"seconds":"36","nanos":400000000},"endTime":{"seconds":"36","nanos":700000000},"word":"depend"},{"startTime":{"seconds":"36","nanos":700000000},"endTime":{"seconds":"36","nanos":900000000},"word":"upon"},{"startTime":{"seconds":"36","nanos":900000000},"endTime":{"seconds":"38","nanos":400000000},"word":"its"},{"startTime":{"seconds":"38","nanos":400000000},"endTime":{"seconds":"38","nanos":700000000},"word":"also"},{"startTime":{"seconds":"38","nanos":700000000},"endTime":{"seconds":"39"},"word":"set"},{"startTime":{"seconds":"39"},"endTime":{"seconds":"39"},"word":"up"},{"startTime":{"seconds":"39"},"endTime":{"seconds":"39","nanos":300000000},"word":"in"},{"startTime":{"seconds":"39","nanos":300000000},"endTime":{"seconds":"39","nanos":300000000},"word":"a"},{"startTime":{"seconds":"39","nanos":300000000},"endTime":{"seconds":"40","nanos":100000000},"word":"hierarchical"},{"startTime":{"seconds":"40","nanos":100000000},"endTime":{"seconds":"40","nanos":500000000},"word":"way"},{"startTime":{"seconds":"40","nanos":500000000},"endTime":{"seconds":"41","nanos":100000000},"word":"for"},{"startTime":{"seconds":"41","nanos":100000000},"endTime":{"seconds":"41","nanos":600000000},"word":"scalability"},{"startTime":{"seconds":"41","nanos":600000000},"endTime":{"seconds":"41","nanos":800000000},"word":"and"},{"startTime":{"seconds":"41","nanos":800000000},"endTime":{"seconds":"41","nanos":900000000},"word":"a"},{"startTime":{"seconds":"41","nanos":900000000},"endTime":{"seconds":"42","nanos":100000000},"word":"variety"},{"startTime":{"seconds":"42","nanos":100000000},"endTime":{"seconds":"42","nanos":300000000},"word":"of"},{"startTime":{"seconds":"42","nanos":300000000},"endTime":{"seconds":"42","nanos":400000000},"word":"other"},{"startTime":{"seconds":"42","nanos":400000000},"endTime":{"seconds":"43","nanos":200000000},"word":"reasons"},{"startTime":{"seconds":"43","nanos":200000000},"endTime":{"seconds":"44","nanos":100000000},"word":"so"},{"startTime":{"seconds":"44","nanos":100000000},"endTime":{"seconds":"44","nanos":300000000},"word":"that"},{"startTime":{"seconds":"44","nanos":300000000},"endTime":{"seconds":"44","nanos":500000000},"word":"we"},{"startTime":{"seconds":"44","nanos":500000000},"endTime":{"seconds":"46","nanos":400000000},"word":"can"},{"startTime":{"seconds":"46","nanos":400000000},"endTime":{"seconds":"47"},"word":"reasonably"},{"startTime":{"seconds":"47"},"endTime":{"seconds":"47","nanos":500000000},"word":"refer"},{"startTime":{"seconds":"47","nanos":500000000},"endTime":{"seconds":"47","nanos":600000000},"word":"to"},{"startTime":{"seconds":"47","nanos":600000000},"endTime":{"seconds":"47","nanos":700000000},"word":"these"},{"startTime":{"seconds":"47","nanos":700000000},"endTime":{"seconds":"48","nanos":300000000},"word":"names."},{"startTime":{"seconds":"48","nanos":300000000},"endTime":{"seconds":"48","nanos":400000000},"word":"And"},{"startTime":{"seconds":"48","nanos":400000000},"endTime":{"seconds":"49","nanos":500000000},"word":"then"},{"startTime":{"seconds":"49","nanos":500000000},"endTime":{"seconds":"49","nanos":700000000},"word":"also"},{"startTime":{"seconds":"49","nanos":700000000},"endTime":{"seconds":"50","nanos":400000000},"word":"what"},{"startTime":{"seconds":"50","nanos":400000000},"endTime":{"seconds":"50","nanos":900000000},"word":"address"},{"startTime":{"seconds":"50","nanos":900000000},"endTime":{"seconds":"51","nanos":100000000},"word":"is"},{"startTime":{"seconds":"51","nanos":100000000},"endTime":{"seconds":"51","nanos":800000000},"word":"and"},{"startTime":{"seconds":"51","nanos":800000000},"endTime":{"seconds":"52","nanos":200000000},"word":"servers"},{"startTime":{"seconds":"52","nanos":200000000},"endTime":{"seconds":"52","nanos":400000000},"word":"would"},{"startTime":{"seconds":"52","nanos":400000000},"endTime":{"seconds":"52","nanos":500000000},"word":"be"},{"startTime":{"seconds":"52","nanos":500000000},"endTime":{"seconds":"53","nanos":300000000},"word":"corresponding"},{"startTime":{"seconds":"53","nanos":300000000},"endTime":{"seconds":"53","nanos":400000000},"word":"to"},{"startTime":{"seconds":"53","nanos":400000000},"endTime":{"seconds":"53","nanos":600000000},"word":"them."},{"startTime":{"seconds":"53","nanos":600000000},"endTime":{"seconds":"54"},"word":"It"},{"startTime":{"seconds":"54"},"endTime":{"seconds":"54"},"word":"also"},{"startTime":{"seconds":"54"},"endTime":{"seconds":"54","nanos":500000000},"word":"incorporates"},{"startTime":{"seconds":"54","nanos":500000000},"endTime":{"seconds":"55","nanos":400000000},"word":"cashing"},{"startTime":{"seconds":"55","nanos":400000000},"endTime":{"seconds":"56","nanos":400000000},"word":"so"},{"startTime":{"seconds":"56","nanos":400000000},"endTime":{"seconds":"56","nanos":600000000},"word":"that"},{"startTime":{"seconds":"56","nanos":600000000},"endTime":{"seconds":"56","nanos":700000000},"word":"we"},{"startTime":{"seconds":"56","nanos":700000000},"endTime":{"seconds":"56","nanos":800000000},"word":"have"},{"startTime":{"seconds":"56","nanos":800000000},"endTime":{"seconds":"57","nanos":600000000},"word":"mappings"},{"startTime":{"seconds":"57","nanos":600000000},"endTime":{"seconds":"58","nanos":500000000},"word":"from"}]}]},{"alternatives":[{"transcript":"Names tour from IP addresses.","confidence":0.7494583129882812,"words":[{"startTime":{"seconds":"59","nanos":400000000},"endTime":{"seconds":"60","nanos":300000000},"word":"Names"},{"startTime":{"seconds":"60","nanos":300000000},"endTime":{"seconds":"60","nanos":800000000},"word":"tour"},{"startTime":{"seconds":"60","nanos":800000000},"endTime":{"seconds":"61"},"word":"from"},{"startTime":{"seconds":"61"},"endTime":{"seconds":"61","nanos":800000000},"word":"IP"},{"startTime":{"seconds":"61","nanos":800000000},"endTime":{"seconds":"62","nanos":100000000},"word":"addresses."}]}]},{"alternatives":[{"transcript":" And then we'll talk about some of the inner workings of DNS as well, such as DNS resolvers and servers how queries and DNS and the DNS protocol work there iterative and recursive versions will talk about how cashing works. And when timeouts Whitaker, we'll talk a little bit about how to do reverse lookups and will show some demonstration of using the dick utility hour, which is a Unix base tool for carrying information within DNS. Let's just quickly compare hostname to versus IP addresses. So whose names will be in demonic name that we appreciate us humans, where as as we've already discussed IP addresses at length. Those are numerical address for those that are necessary for routers.","confidence":0.9657279253005981,"words":[{"startTime":{"seconds":"63","nanos":500000000},"endTime":{"seconds":"63","nanos":900000000},"word":"And"},{"startTime":{"seconds":"63","nanos":900000000},"endTime":{"seconds":"64"},"word":"then"},{"startTime":{"seconds":"64"},"endTime":{"seconds":"64","nanos":300000000},"word":"we'll"},{"startTime":{"seconds":"64","nanos":300000000},"endTime":{"seconds":"64","nanos":700000000},"word":"talk"},{"startTime":{"seconds":"64","nanos":700000000},"endTime":{"seconds":"64","nanos":900000000},"word":"about"},{"startTime":{"seconds":"64","nanos":900000000},"endTime":{"seconds":"65","nanos":200000000},"word":"some"},{"startTime":{"seconds":"65","nanos":200000000},"endTime":{"seconds":"65","nanos":200000000},"word":"of"},{"startTime":{"seconds":"65","nanos":200000000},"endTime":{"seconds":"65","nanos":300000000},"word":"the"},{"startTime":{"seconds":"65","nanos":300000000},"endTime":{"seconds":"65","nanos":500000000},"word":"inner"},{"startTime":{"seconds":"65","nanos":500000000},"endTime":{"seconds":"65","nanos":800000000},"word":"workings"},{"startTime":{"seconds":"65","nanos":800000000},"endTime":{"seconds":"66","nanos":100000000},"word":"of"},{"startTime":{"seconds":"66","nanos":100000000},"endTime":{"seconds":"66","nanos":600000000},"word":"DNS"},{"startTime":{"seconds":"66","nanos":600000000},"endTime":{"seconds":"66","nanos":800000000},"word":"as"},{"startTime":{"seconds":"66","nanos":800000000},"endTime":{"seconds":"67","nanos":200000000},"word":"well,"},{"startTime":{"seconds":"67","nanos":200000000},"endTime":{"seconds":"67","nanos":600000000},"word":"such"},{"startTime":{"seconds":"67","nanos":600000000},"endTime":{"seconds":"67","nanos":900000000},"word":"as"},{"startTime":{"seconds":"67","nanos":900000000},"endTime":{"seconds":"68","nanos":300000000},"word":"DNS"},{"startTime":{"seconds":"68","nanos":300000000},"endTime":{"seconds":"68","nanos":800000000},"word":"resolvers"},{"startTime":{"seconds":"68","nanos":800000000},"endTime":{"seconds":"69","nanos":100000000},"word":"and"},{"startTime":{"seconds":"69","nanos":100000000},"endTime":{"seconds":"69","nanos":700000000},"word":"servers"},{"startTime":{"seconds":"69","nanos":700000000},"endTime":{"seconds":"70","nanos":700000000},"word":"how"},{"startTime":{"seconds":"70","nanos":700000000},"endTime":{"seconds":"71","nanos":300000000},"word":"queries"},{"startTime":{"seconds":"71","nanos":300000000},"endTime":{"seconds":"71","nanos":500000000},"word":"and"},{"startTime":{"seconds":"71","nanos":500000000},"endTime":{"seconds":"71","nanos":900000000},"word":"DNS"},{"startTime":{"seconds":"71","nanos":900000000},"endTime":{"seconds":"72","nanos":400000000},"word":"and"},{"startTime":{"seconds":"72","nanos":400000000},"endTime":{"seconds":"72","nanos":400000000},"word":"the"},{"startTime":{"seconds":"72","nanos":400000000},"endTime":{"seconds":"72","nanos":800000000},"word":"DNS"},{"startTime":{"seconds":"72","nanos":800000000},"endTime":{"seconds":"73","nanos":200000000},"word":"protocol"},{"startTime":{"seconds":"73","nanos":200000000},"endTime":{"seconds":"73","nanos":600000000},"word":"work"},{"startTime":{"seconds":"73","nanos":600000000},"endTime":{"seconds":"74","nanos":300000000},"word":"there"},{"startTime":{"seconds":"74","nanos":300000000},"endTime":{"seconds":"74","nanos":800000000},"word":"iterative"},{"startTime":{"seconds":"74","nanos":800000000},"endTime":{"seconds":"74","nanos":900000000},"word":"and"},{"startTime":{"seconds":"74","nanos":900000000},"endTime":{"seconds":"75","nanos":300000000},"word":"recursive"},{"startTime":{"seconds":"75","nanos":300000000},"endTime":{"seconds":"76","nanos":100000000},"word":"versions"},{"startTime":{"seconds":"76","nanos":100000000},"endTime":{"seconds":"77","nanos":800000000},"word":"will"},{"startTime":{"seconds":"77","nanos":800000000},"endTime":{"seconds":"78","nanos":100000000},"word":"talk"},{"startTime":{"seconds":"78","nanos":100000000},"endTime":{"seconds":"78","nanos":200000000},"word":"about"},{"startTime":{"seconds":"78","nanos":200000000},"endTime":{"seconds":"78","nanos":700000000},"word":"how"},{"startTime":{"seconds":"78","nanos":700000000},"endTime":{"seconds":"79","nanos":200000000},"word":"cashing"},{"startTime":{"seconds":"79","nanos":200000000},"endTime":{"seconds":"79","nanos":600000000},"word":"works."},{"startTime":{"seconds":"79","nanos":600000000},"endTime":{"seconds":"80","nanos":200000000},"word":"And"},{"startTime":{"seconds":"80","nanos":200000000},"endTime":{"seconds":"80","nanos":400000000},"word":"when"},{"startTime":{"seconds":"80","nanos":400000000},"endTime":{"seconds":"80","nanos":900000000},"word":"timeouts"},{"startTime":{"seconds":"80","nanos":900000000},"endTime":{"seconds":"81","nanos":300000000},"word":"Whitaker,"},{"startTime":{"seconds":"81","nanos":300000000},"endTime":{"seconds":"82","nanos":500000000},"word":"we'll"},{"startTime":{"seconds":"82","nanos":500000000},"endTime":{"seconds":"82","nanos":700000000},"word":"talk"},{"startTime":{"seconds":"82","nanos":700000000},"endTime":{"seconds":"82","nanos":700000000},"word":"a"},{"startTime":{"seconds":"82","nanos":700000000},"endTime":{"seconds":"82","nanos":800000000},"word":"little"},{"startTime":{"seconds":"82","nanos":800000000},"endTime":{"seconds":"83"},"word":"bit"},{"startTime":{"seconds":"83"},"endTime":{"seconds":"83","nanos":200000000},"word":"about"},{"startTime":{"seconds":"83","nanos":200000000},"endTime":{"seconds":"83","nanos":400000000},"word":"how"},{"startTime":{"seconds":"83","nanos":400000000},"endTime":{"seconds":"83","nanos":500000000},"word":"to"},{"startTime":{"seconds":"83","nanos":500000000},"endTime":{"seconds":"83","nanos":700000000},"word":"do"},{"startTime":{"seconds":"83","nanos":700000000},"endTime":{"seconds":"83","nanos":900000000},"word":"reverse"},{"startTime":{"seconds":"83","nanos":900000000},"endTime":{"seconds":"84","nanos":900000000},"word":"lookups"},{"startTime":{"seconds":"84","nanos":900000000},"endTime":{"seconds":"85","nanos":800000000},"word":"and"},{"startTime":{"seconds":"85","nanos":800000000},"endTime":{"seconds":"86"},"word":"will"},{"startTime":{"seconds":"86"},"endTime":{"seconds":"86","nanos":200000000},"word":"show"},{"startTime":{"seconds":"86","nanos":200000000},"endTime":{"seconds":"87","nanos":500000000},"word":"some"},{"startTime":{"seconds":"87","nanos":500000000},"endTime":{"seconds":"88","nanos":300000000},"word":"demonstration"},{"startTime":{"seconds":"88","nanos":300000000},"endTime":{"seconds":"88","nanos":400000000},"word":"of"},{"startTime":{"seconds":"88","nanos":400000000},"endTime":{"seconds":"88","nanos":500000000},"word":"using"},{"startTime":{"seconds":"88","nanos":500000000},"endTime":{"seconds":"89"},"word":"the"},{"startTime":{"seconds":"89"},"endTime":{"seconds":"89","nanos":300000000},"word":"dick"},{"startTime":{"seconds":"89","nanos":300000000},"endTime":{"seconds":"89","nanos":900000000},"word":"utility"},{"startTime":{"seconds":"89","nanos":900000000},"endTime":{"seconds":"90","nanos":600000000},"word":"hour,"},{"startTime":{"seconds":"90","nanos":600000000},"endTime":{"seconds":"90","nanos":700000000},"word":"which"},{"startTime":{"seconds":"90","nanos":700000000},"endTime":{"seconds":"90","nanos":800000000},"word":"is"},{"startTime":{"seconds":"90","nanos":800000000},"endTime":{"seconds":"91"},"word":"a"},{"startTime":{"seconds":"91"},"endTime":{"seconds":"91","nanos":300000000},"word":"Unix"},{"startTime":{"seconds":"91","nanos":300000000},"endTime":{"seconds":"91","nanos":500000000},"word":"base"},{"startTime":{"seconds":"91","nanos":500000000},"endTime":{"seconds":"92"},"word":"tool"},{"startTime":{"seconds":"92"},"endTime":{"seconds":"92","nanos":200000000},"word":"for"},{"startTime":{"seconds":"92","nanos":200000000},"endTime":{"seconds":"92","nanos":700000000},"word":"carrying"},{"startTime":{"seconds":"92","nanos":700000000},"endTime":{"seconds":"93","nanos":400000000},"word":"information"},{"startTime":{"seconds":"93","nanos":400000000},"endTime":{"seconds":"94","nanos":100000000},"word":"within"},{"startTime":{"seconds":"94","nanos":100000000},"endTime":{"seconds":"94","nanos":600000000},"word":"DNS."},{"startTime":{"seconds":"94","nanos":600000000},"endTime":{"seconds":"95","nanos":600000000},"word":"Let's"},{"startTime":{"seconds":"95","nanos":600000000},"endTime":{"seconds":"95","nanos":700000000},"word":"just"},{"startTime":{"seconds":"95","nanos":700000000},"endTime":{"seconds":"96"},"word":"quickly"},{"startTime":{"seconds":"96"},"endTime":{"seconds":"96","nanos":400000000},"word":"compare"},{"startTime":{"seconds":"96","nanos":400000000},"endTime":{"seconds":"96","nanos":800000000},"word":"hostname"},{"startTime":{"seconds":"96","nanos":800000000},"endTime":{"seconds":"97"},"word":"to"},{"startTime":{"seconds":"97"},"endTime":{"seconds":"97","nanos":300000000},"word":"versus"},{"startTime":{"seconds":"97","nanos":300000000},"endTime":{"seconds":"97","nanos":700000000},"word":"IP"},{"startTime":{"seconds":"97","nanos":700000000},"endTime":{"seconds":"98","nanos":300000000},"word":"addresses."},{"startTime":{"seconds":"98","nanos":300000000},"endTime":{"seconds":"99","nanos":500000000},"word":"So"},{"startTime":{"seconds":"99","nanos":500000000},"endTime":{"seconds":"99","nanos":800000000},"word":"whose"},{"startTime":{"seconds":"99","nanos":800000000},"endTime":{"seconds":"100","nanos":300000000},"word":"names"},{"startTime":{"seconds":"100","nanos":300000000},"endTime":{"seconds":"100","nanos":700000000},"word":"will"},{"startTime":{"seconds":"100","nanos":700000000},"endTime":{"seconds":"100","nanos":800000000},"word":"be"},{"startTime":{"seconds":"100","nanos":800000000},"endTime":{"seconds":"101"},"word":"in"},{"startTime":{"seconds":"101"},"endTime":{"seconds":"101","nanos":300000000},"word":"demonic"},{"startTime":{"seconds":"101","nanos":300000000},"endTime":{"seconds":"101","nanos":700000000},"word":"name"},{"startTime":{"seconds":"101","nanos":700000000},"endTime":{"seconds":"102"},"word":"that"},{"startTime":{"seconds":"102"},"endTime":{"seconds":"102","nanos":200000000},"word":"we"},{"startTime":{"seconds":"102","nanos":200000000},"endTime":{"seconds":"102","nanos":500000000},"word":"appreciate"},{"startTime":{"seconds":"102","nanos":500000000},"endTime":{"seconds":"102","nanos":900000000},"word":"us"},{"startTime":{"seconds":"102","nanos":900000000},"endTime":{"seconds":"103","nanos":400000000},"word":"humans,"},{"startTime":{"seconds":"103","nanos":400000000},"endTime":{"seconds":"103","nanos":800000000},"word":"where"},{"startTime":{"seconds":"103","nanos":800000000},"endTime":{"seconds":"104"},"word":"as"},{"startTime":{"seconds":"104"},"endTime":{"seconds":"104","nanos":600000000},"word":"as"},{"startTime":{"seconds":"104","nanos":600000000},"endTime":{"seconds":"104","nanos":800000000},"word":"we've"},{"startTime":{"seconds":"104","nanos":800000000},"endTime":{"seconds":"104","nanos":900000000},"word":"already"},{"startTime":{"seconds":"104","nanos":900000000},"endTime":{"seconds":"105","nanos":100000000},"word":"discussed"},{"startTime":{"seconds":"105","nanos":100000000},"endTime":{"seconds":"105","nanos":800000000},"word":"IP"},{"startTime":{"seconds":"105","nanos":800000000},"endTime":{"seconds":"106","nanos":300000000},"word":"addresses"},{"startTime":{"seconds":"106","nanos":300000000},"endTime":{"seconds":"106","nanos":400000000},"word":"at"},{"startTime":{"seconds":"106","nanos":400000000},"endTime":{"seconds":"106","nanos":800000000},"word":"length."},{"startTime":{"seconds":"106","nanos":800000000},"endTime":{"seconds":"107","nanos":700000000},"word":"Those"},{"startTime":{"seconds":"107","nanos":700000000},"endTime":{"seconds":"108","nanos":100000000},"word":"are"},{"startTime":{"seconds":"108","nanos":100000000},"endTime":{"seconds":"109"},"word":"numerical"},{"startTime":{"seconds":"109"},"endTime":{"seconds":"109","nanos":100000000},"word":"address"},{"startTime":{"seconds":"109","nanos":100000000},"endTime":{"seconds":"109","nanos":500000000},"word":"for"},{"startTime":{"seconds":"109","nanos":500000000},"endTime":{"seconds":"109","nanos":600000000},"word":"those"},{"startTime":{"seconds":"109","nanos":600000000},"endTime":{"seconds":"109","nanos":700000000},"word":"that"},{"startTime":{"seconds":"109","nanos":700000000},"endTime":{"seconds":"109","nanos":900000000},"word":"are"},{"startTime":{"seconds":"109","nanos":900000000},"endTime":{"seconds":"110","nanos":200000000},"word":"necessary"},{"startTime":{"seconds":"110","nanos":200000000},"endTime":{"seconds":"110","nanos":700000000},"word":"for"},{"startTime":{"seconds":"110","nanos":700000000},"endTime":{"seconds":"111","nanos":400000000},"word":"routers."}]}]},{"alternatives":[{"transcript":" Host names will, of course, be variable length and will now use the full alphabet of characters. Where is IP, addresses, were fixed length and always responded under the Hardison. Binary number.","confidence":0.8814182877540588,"words":[{"startTime":{"seconds":"112","nanos":200000000},"endTime":{"seconds":"113","nanos":800000000},"word":"Host"},{"startTime":{"seconds":"113","nanos":800000000},"endTime":{"seconds":"114","nanos":100000000},"word":"names"},{"startTime":{"seconds":"114","nanos":100000000},"endTime":{"seconds":"114","nanos":200000000},"word":"will,"},{"startTime":{"seconds":"114","nanos":200000000},"endTime":{"seconds":"114","nanos":300000000},"word":"of"},{"startTime":{"seconds":"114","nanos":300000000},"endTime":{"seconds":"114","nanos":400000000},"word":"course,"},{"startTime":{"seconds":"114","nanos":400000000},"endTime":{"seconds":"114","nanos":700000000},"word":"be"},{"startTime":{"seconds":"114","nanos":700000000},"endTime":{"seconds":"115","nanos":100000000},"word":"variable"},{"startTime":{"seconds":"115","nanos":100000000},"endTime":{"seconds":"115","nanos":400000000},"word":"length"},{"startTime":{"seconds":"115","nanos":400000000},"endTime":{"seconds":"115","nanos":700000000},"word":"and"},{"startTime":{"seconds":"115","nanos":700000000},"endTime":{"seconds":"115","nanos":800000000},"word":"will"},{"startTime":{"seconds":"115","nanos":800000000},"endTime":{"seconds":"115","nanos":900000000},"word":"now"},{"startTime":{"seconds":"115","nanos":900000000},"endTime":{"seconds":"116","nanos":400000000},"word":"use"},{"startTime":{"seconds":"116","nanos":400000000},"endTime":{"seconds":"116","nanos":600000000},"word":"the"},{"startTime":{"seconds":"116","nanos":600000000},"endTime":{"seconds":"116","nanos":800000000},"word":"full"},{"startTime":{"seconds":"116","nanos":800000000},"endTime":{"seconds":"117"},"word":"alphabet"},{"startTime":{"seconds":"117"},"endTime":{"seconds":"117","nanos":300000000},"word":"of"},{"startTime":{"seconds":"117","nanos":300000000},"endTime":{"seconds":"118"},"word":"characters."},{"startTime":{"seconds":"118"},"endTime":{"seconds":"119","nanos":600000000},"word":"Where"},{"startTime":{"seconds":"119","nanos":600000000},"endTime":{"seconds":"119","nanos":800000000},"word":"is"},{"startTime":{"seconds":"119","nanos":800000000},"endTime":{"seconds":"120","nanos":100000000},"word":"IP,"},{"startTime":{"seconds":"120","nanos":100000000},"endTime":{"seconds":"120","nanos":700000000},"word":"addresses,"},{"startTime":{"seconds":"120","nanos":700000000},"endTime":{"seconds":"120","nanos":900000000},"word":"were"},{"startTime":{"seconds":"120","nanos":900000000},"endTime":{"seconds":"121","nanos":200000000},"word":"fixed"},{"startTime":{"seconds":"121","nanos":200000000},"endTime":{"seconds":"121","nanos":700000000},"word":"length"},{"startTime":{"seconds":"121","nanos":700000000},"endTime":{"seconds":"122","nanos":200000000},"word":"and"},{"startTime":{"seconds":"122","nanos":200000000},"endTime":{"seconds":"122","nanos":400000000},"word":"always"},{"startTime":{"seconds":"122","nanos":400000000},"endTime":{"seconds":"123","nanos":300000000},"word":"responded"},{"startTime":{"seconds":"123","nanos":300000000},"endTime":{"seconds":"124","nanos":100000000},"word":"under"},{"startTime":{"seconds":"124","nanos":100000000},"endTime":{"seconds":"124","nanos":100000000},"word":"the"},{"startTime":{"seconds":"124","nanos":100000000},"endTime":{"seconds":"124","nanos":700000000},"word":"Hardison."},{"startTime":{"seconds":"124","nanos":700000000},"endTime":{"seconds":"125","nanos":100000000},"word":"Binary"},{"startTime":{"seconds":"125","nanos":100000000},"endTime":{"seconds":"125","nanos":500000000},"word":"number."}]}]},{"alternatives":[{"transcript":" The host names are going to provide little if any information about a location where as IP addresses were defined in a hierarchical way and they were related to the hosts location so that we can perform that routing process to get information where it needs to go. So do some examples of course some hosts names like www.cnn.com BBC. Co. Uk would provide a little location information and these are coarser easier to remember than the numerical quantities and IP addresses below.","confidence":0.9629957675933838,"words":[{"startTime":{"seconds":"126","nanos":500000000},"endTime":{"seconds":"127","nanos":900000000},"word":"The"},{"startTime":{"seconds":"127","nanos":900000000},"endTime":{"seconds":"128","nanos":100000000},"word":"host"},{"startTime":{"seconds":"128","nanos":100000000},"endTime":{"seconds":"128","nanos":500000000},"word":"names"},{"startTime":{"seconds":"128","nanos":500000000},"endTime":{"seconds":"128","nanos":700000000},"word":"are"},{"startTime":{"seconds":"128","nanos":700000000},"endTime":{"seconds":"128","nanos":800000000},"word":"going"},{"startTime":{"seconds":"128","nanos":800000000},"endTime":{"seconds":"128","nanos":900000000},"word":"to"},{"startTime":{"seconds":"128","nanos":900000000},"endTime":{"seconds":"129","nanos":100000000},"word":"provide"},{"startTime":{"seconds":"129","nanos":100000000},"endTime":{"seconds":"129","nanos":600000000},"word":"little"},{"startTime":{"seconds":"129","nanos":600000000},"endTime":{"seconds":"130"},"word":"if"},{"startTime":{"seconds":"130"},"endTime":{"seconds":"130","nanos":200000000},"word":"any"},{"startTime":{"seconds":"130","nanos":200000000},"endTime":{"seconds":"130","nanos":900000000},"word":"information"},{"startTime":{"seconds":"130","nanos":900000000},"endTime":{"seconds":"131","nanos":100000000},"word":"about"},{"startTime":{"seconds":"131","nanos":100000000},"endTime":{"seconds":"131","nanos":400000000},"word":"a"},{"startTime":{"seconds":"131","nanos":400000000},"endTime":{"seconds":"132"},"word":"location"},{"startTime":{"seconds":"132"},"endTime":{"seconds":"133","nanos":400000000},"word":"where"},{"startTime":{"seconds":"133","nanos":400000000},"endTime":{"seconds":"133","nanos":700000000},"word":"as"},{"startTime":{"seconds":"133","nanos":700000000},"endTime":{"seconds":"134","nanos":200000000},"word":"IP"},{"startTime":{"seconds":"134","nanos":200000000},"endTime":{"seconds":"134","nanos":800000000},"word":"addresses"},{"startTime":{"seconds":"134","nanos":800000000},"endTime":{"seconds":"135","nanos":100000000},"word":"were"},{"startTime":{"seconds":"135","nanos":100000000},"endTime":{"seconds":"136","nanos":100000000},"word":"defined"},{"startTime":{"seconds":"136","nanos":100000000},"endTime":{"seconds":"136","nanos":200000000},"word":"in"},{"startTime":{"seconds":"136","nanos":200000000},"endTime":{"seconds":"136","nanos":300000000},"word":"a"},{"startTime":{"seconds":"136","nanos":300000000},"endTime":{"seconds":"136","nanos":800000000},"word":"hierarchical"},{"startTime":{"seconds":"136","nanos":800000000},"endTime":{"seconds":"137","nanos":300000000},"word":"way"},{"startTime":{"seconds":"137","nanos":300000000},"endTime":{"seconds":"138"},"word":"and"},{"startTime":{"seconds":"138"},"endTime":{"seconds":"138","nanos":100000000},"word":"they"},{"startTime":{"seconds":"138","nanos":100000000},"endTime":{"seconds":"138","nanos":400000000},"word":"were"},{"startTime":{"seconds":"138","nanos":400000000},"endTime":{"seconds":"139"},"word":"related"},{"startTime":{"seconds":"139"},"endTime":{"seconds":"139"},"word":"to"},{"startTime":{"seconds":"139"},"endTime":{"seconds":"139","nanos":200000000},"word":"the"},{"startTime":{"seconds":"139","nanos":200000000},"endTime":{"seconds":"139","nanos":500000000},"word":"hosts"},{"startTime":{"seconds":"139","nanos":500000000},"endTime":{"seconds":"140","nanos":100000000},"word":"location"},{"startTime":{"seconds":"140","nanos":100000000},"endTime":{"seconds":"140","nanos":400000000},"word":"so"},{"startTime":{"seconds":"140","nanos":400000000},"endTime":{"seconds":"140","nanos":400000000},"word":"that"},{"startTime":{"seconds":"140","nanos":400000000},"endTime":{"seconds":"140","nanos":700000000},"word":"we"},{"startTime":{"seconds":"140","nanos":700000000},"endTime":{"seconds":"140","nanos":800000000},"word":"can"},{"startTime":{"seconds":"140","nanos":800000000},"endTime":{"seconds":"141","nanos":100000000},"word":"perform"},{"startTime":{"seconds":"141","nanos":100000000},"endTime":{"seconds":"141","nanos":400000000},"word":"that"},{"startTime":{"seconds":"141","nanos":400000000},"endTime":{"seconds":"141","nanos":800000000},"word":"routing"},{"startTime":{"seconds":"141","nanos":800000000},"endTime":{"seconds":"143","nanos":300000000},"word":"process"},{"startTime":{"seconds":"143","nanos":300000000},"endTime":{"seconds":"143","nanos":500000000},"word":"to"},{"startTime":{"seconds":"143","nanos":500000000},"endTime":{"seconds":"143","nanos":700000000},"word":"get"},{"startTime":{"seconds":"143","nanos":700000000},"endTime":{"seconds":"144"},"word":"information"},{"startTime":{"seconds":"144"},"endTime":{"seconds":"144","nanos":600000000},"word":"where"},{"startTime":{"seconds":"144","nanos":600000000},"endTime":{"seconds":"144","nanos":700000000},"word":"it"},{"startTime":{"seconds":"144","nanos":700000000},"endTime":{"seconds":"145"},"word":"needs"},{"startTime":{"seconds":"145"},"endTime":{"seconds":"145","nanos":100000000},"word":"to"},{"startTime":{"seconds":"145","nanos":100000000},"endTime":{"seconds":"145","nanos":200000000},"word":"go."},{"startTime":{"seconds":"145","nanos":200000000},"endTime":{"seconds":"146","nanos":100000000},"word":"So"},{"startTime":{"seconds":"146","nanos":100000000},"endTime":{"seconds":"146","nanos":200000000},"word":"do"},{"startTime":{"seconds":"146","nanos":200000000},"endTime":{"seconds":"146","nanos":400000000},"word":"some"},{"startTime":{"seconds":"146","nanos":400000000},"endTime":{"seconds":"147"},"word":"examples"},{"startTime":{"seconds":"147"},"endTime":{"seconds":"147"},"word":"of"},{"startTime":{"seconds":"147"},"endTime":{"seconds":"147","nanos":400000000},"word":"course"},{"startTime":{"seconds":"147","nanos":400000000},"endTime":{"seconds":"148","nanos":300000000},"word":"some"},{"startTime":{"seconds":"148","nanos":300000000},"endTime":{"seconds":"148","nanos":600000000},"word":"hosts"},{"startTime":{"seconds":"148","nanos":600000000},"endTime":{"seconds":"148","nanos":900000000},"word":"names"},{"startTime":{"seconds":"148","nanos":900000000},"endTime":{"seconds":"149","nanos":300000000},"word":"like"},{"startTime":{"seconds":"149","nanos":300000000},"endTime":{"seconds":"150","nanos":900000000},"word":"www.cnn.com"},{"startTime":{"seconds":"150","nanos":900000000},"endTime":{"seconds":"153","nanos":300000000},"word":"BBC."},{"startTime":{"seconds":"153","nanos":300000000},"endTime":{"seconds":"153","nanos":500000000},"word":"Co."},{"startTime":{"seconds":"153","nanos":500000000},"endTime":{"seconds":"153","nanos":700000000},"word":"Uk"},{"startTime":{"seconds":"153","nanos":700000000},"endTime":{"seconds":"154","nanos":300000000},"word":"would"},{"startTime":{"seconds":"154","nanos":300000000},"endTime":{"seconds":"154","nanos":500000000},"word":"provide"},{"startTime":{"seconds":"154","nanos":500000000},"endTime":{"seconds":"154","nanos":700000000},"word":"a"},{"startTime":{"seconds":"154","nanos":700000000},"endTime":{"seconds":"154","nanos":800000000},"word":"little"},{"startTime":{"seconds":"154","nanos":800000000},"endTime":{"seconds":"155","nanos":500000000},"word":"location"},{"startTime":{"seconds":"155","nanos":500000000},"endTime":{"seconds":"155","nanos":700000000},"word":"information"},{"startTime":{"seconds":"155","nanos":700000000},"endTime":{"seconds":"157","nanos":900000000},"word":"and"},{"startTime":{"seconds":"157","nanos":900000000},"endTime":{"seconds":"158","nanos":200000000},"word":"these"},{"startTime":{"seconds":"158","nanos":200000000},"endTime":{"seconds":"158","nanos":400000000},"word":"are"},{"startTime":{"seconds":"158","nanos":400000000},"endTime":{"seconds":"158","nanos":800000000},"word":"coarser"},{"startTime":{"seconds":"158","nanos":800000000},"endTime":{"seconds":"159","nanos":100000000},"word":"easier"},{"startTime":{"seconds":"159","nanos":100000000},"endTime":{"seconds":"159","nanos":200000000},"word":"to"},{"startTime":{"seconds":"159","nanos":200000000},"endTime":{"seconds":"159","nanos":400000000},"word":"remember"},{"startTime":{"seconds":"159","nanos":400000000},"endTime":{"seconds":"159","nanos":800000000},"word":"than"},{"startTime":{"seconds":"159","nanos":800000000},"endTime":{"seconds":"159","nanos":900000000},"word":"the"},{"startTime":{"seconds":"159","nanos":900000000},"endTime":{"seconds":"160","nanos":500000000},"word":"numerical"},{"startTime":{"seconds":"160","nanos":500000000},"endTime":{"seconds":"161","nanos":500000000},"word":"quantities"},{"startTime":{"seconds":"161","nanos":500000000},"endTime":{"seconds":"163","nanos":200000000},"word":"and"},{"startTime":{"seconds":"163","nanos":200000000},"endTime":{"seconds":"163","nanos":600000000},"word":"IP"},{"startTime":{"seconds":"163","nanos":600000000},"endTime":{"seconds":"164","nanos":200000000},"word":"addresses"},{"startTime":{"seconds":"164","nanos":200000000},"endTime":{"seconds":"164","nanos":600000000},"word":"below."}]}]},{"alternatives":[{"transcript":" How do we separate the naming from the addressing? And why do we do this? Well, of course names are easier to remember. The other reason is that underneath the addresses could change. Perhaps we change the server that's running the toasting the website CNN.com, or perhaps we change a service provider. The other thing is a name could actually about to multiple IP addresses, perhaps for load balancing or scalability reasons. We have multiple replicas of a website. So handling load balancing a reducing late and see if perhaps we put a server hosting CNN.com saying different country so that there is always one close by to people likely to try to access that server.","confidence":0.9664708375930786,"words":[{"startTime":{"seconds":"166","nanos":500000000},"endTime":{"seconds":"167"},"word":"How"},{"startTime":{"seconds":"167"},"endTime":{"seconds":"167","nanos":100000000},"word":"do"},{"startTime":{"seconds":"167","nanos":100000000},"endTime":{"seconds":"167","nanos":200000000},"word":"we"},{"startTime":{"seconds":"167","nanos":200000000},"endTime":{"seconds":"167","nanos":700000000},"word":"separate"},{"startTime":{"seconds":"167","nanos":700000000},"endTime":{"seconds":"168","nanos":700000000},"word":"the"},{"startTime":{"seconds":"168","nanos":700000000},"endTime":{"seconds":"169"},"word":"naming"},{"startTime":{"seconds":"169"},"endTime":{"seconds":"169","nanos":300000000},"word":"from"},{"startTime":{"seconds":"169","nanos":300000000},"endTime":{"seconds":"169","nanos":400000000},"word":"the"},{"startTime":{"seconds":"169","nanos":400000000},"endTime":{"seconds":"170"},"word":"addressing?"},{"startTime":{"seconds":"170"},"endTime":{"seconds":"170","nanos":100000000},"word":"And"},{"startTime":{"seconds":"170","nanos":100000000},"endTime":{"seconds":"170","nanos":300000000},"word":"why"},{"startTime":{"seconds":"170","nanos":300000000},"endTime":{"seconds":"170","nanos":400000000},"word":"do"},{"startTime":{"seconds":"170","nanos":400000000},"endTime":{"seconds":"170","nanos":400000000},"word":"we"},{"startTime":{"seconds":"170","nanos":400000000},"endTime":{"seconds":"170","nanos":600000000},"word":"do"},{"startTime":{"seconds":"170","nanos":600000000},"endTime":{"seconds":"170","nanos":700000000},"word":"this?"},{"startTime":{"seconds":"170","nanos":700000000},"endTime":{"seconds":"171"},"word":"Well,"},{"startTime":{"seconds":"171"},"endTime":{"seconds":"171"},"word":"of"},{"startTime":{"seconds":"171"},"endTime":{"seconds":"171","nanos":200000000},"word":"course"},{"startTime":{"seconds":"171","nanos":200000000},"endTime":{"seconds":"171","nanos":700000000},"word":"names"},{"startTime":{"seconds":"171","nanos":700000000},"endTime":{"seconds":"171","nanos":800000000},"word":"are"},{"startTime":{"seconds":"171","nanos":800000000},"endTime":{"seconds":"172","nanos":100000000},"word":"easier"},{"startTime":{"seconds":"172","nanos":100000000},"endTime":{"seconds":"172","nanos":500000000},"word":"to"},{"startTime":{"seconds":"172","nanos":500000000},"endTime":{"seconds":"172","nanos":700000000},"word":"remember."},{"startTime":{"seconds":"172","nanos":700000000},"endTime":{"seconds":"174","nanos":200000000},"word":"The"},{"startTime":{"seconds":"174","nanos":200000000},"endTime":{"seconds":"174","nanos":400000000},"word":"other"},{"startTime":{"seconds":"174","nanos":400000000},"endTime":{"seconds":"175","nanos":400000000},"word":"reason"},{"startTime":{"seconds":"175","nanos":400000000},"endTime":{"seconds":"175","nanos":400000000},"word":"is"},{"startTime":{"seconds":"175","nanos":400000000},"endTime":{"seconds":"175","nanos":600000000},"word":"that"},{"startTime":{"seconds":"175","nanos":600000000},"endTime":{"seconds":"176","nanos":100000000},"word":"underneath"},{"startTime":{"seconds":"176","nanos":100000000},"endTime":{"seconds":"176","nanos":400000000},"word":"the"},{"startTime":{"seconds":"176","nanos":400000000},"endTime":{"seconds":"176","nanos":800000000},"word":"addresses"},{"startTime":{"seconds":"176","nanos":800000000},"endTime":{"seconds":"177","nanos":100000000},"word":"could"},{"startTime":{"seconds":"177","nanos":100000000},"endTime":{"seconds":"177","nanos":600000000},"word":"change."},{"startTime":{"seconds":"177","nanos":600000000},"endTime":{"seconds":"178","nanos":500000000},"word":"Perhaps"},{"startTime":{"seconds":"178","nanos":500000000},"endTime":{"seconds":"178","nanos":700000000},"word":"we"},{"startTime":{"seconds":"178","nanos":700000000},"endTime":{"seconds":"179","nanos":200000000},"word":"change"},{"startTime":{"seconds":"179","nanos":200000000},"endTime":{"seconds":"179","nanos":400000000},"word":"the"},{"startTime":{"seconds":"179","nanos":400000000},"endTime":{"seconds":"179","nanos":900000000},"word":"server"},{"startTime":{"seconds":"179","nanos":900000000},"endTime":{"seconds":"181","nanos":700000000},"word":"that's"},{"startTime":{"seconds":"181","nanos":700000000},"endTime":{"seconds":"182","nanos":200000000},"word":"running"},{"startTime":{"seconds":"182","nanos":200000000},"endTime":{"seconds":"183"},"word":"the"},{"startTime":{"seconds":"183"},"endTime":{"seconds":"183","nanos":500000000},"word":"toasting"},{"startTime":{"seconds":"183","nanos":500000000},"endTime":{"seconds":"183","nanos":600000000},"word":"the"},{"startTime":{"seconds":"183","nanos":600000000},"endTime":{"seconds":"184","nanos":100000000},"word":"website"},{"startTime":{"seconds":"184","nanos":100000000},"endTime":{"seconds":"184","nanos":500000000},"word":"CNN.com,"},{"startTime":{"seconds":"184","nanos":500000000},"endTime":{"seconds":"186","nanos":300000000},"word":"or"},{"startTime":{"seconds":"186","nanos":300000000},"endTime":{"seconds":"186","nanos":500000000},"word":"perhaps"},{"startTime":{"seconds":"186","nanos":500000000},"endTime":{"seconds":"186","nanos":800000000},"word":"we"},{"startTime":{"seconds":"186","nanos":800000000},"endTime":{"seconds":"187","nanos":100000000},"word":"change"},{"startTime":{"seconds":"187","nanos":100000000},"endTime":{"seconds":"187","nanos":100000000},"word":"a"},{"startTime":{"seconds":"187","nanos":100000000},"endTime":{"seconds":"187","nanos":500000000},"word":"service"},{"startTime":{"seconds":"187","nanos":500000000},"endTime":{"seconds":"187","nanos":700000000},"word":"provider."},{"startTime":{"seconds":"187","nanos":700000000},"endTime":{"seconds":"188","nanos":800000000},"word":"The"},{"startTime":{"seconds":"188","nanos":800000000},"endTime":{"seconds":"189"},"word":"other"},{"startTime":{"seconds":"189"},"endTime":{"seconds":"189","nanos":200000000},"word":"thing"},{"startTime":{"seconds":"189","nanos":200000000},"endTime":{"seconds":"189","nanos":400000000},"word":"is"},{"startTime":{"seconds":"189","nanos":400000000},"endTime":{"seconds":"189","nanos":500000000},"word":"a"},{"startTime":{"seconds":"189","nanos":500000000},"endTime":{"seconds":"189","nanos":900000000},"word":"name"},{"startTime":{"seconds":"189","nanos":900000000},"endTime":{"seconds":"190","nanos":100000000},"word":"could"},{"startTime":{"seconds":"190","nanos":100000000},"endTime":{"seconds":"190","nanos":300000000},"word":"actually"},{"startTime":{"seconds":"190","nanos":300000000},"endTime":{"seconds":"190","nanos":700000000},"word":"about"},{"startTime":{"seconds":"190","nanos":700000000},"endTime":{"seconds":"190","nanos":900000000},"word":"to"},{"startTime":{"seconds":"190","nanos":900000000},"endTime":{"seconds":"191","nanos":300000000},"word":"multiple"},{"startTime":{"seconds":"191","nanos":300000000},"endTime":{"seconds":"191","nanos":500000000},"word":"IP"},{"startTime":{"seconds":"191","nanos":500000000},"endTime":{"seconds":"191","nanos":900000000},"word":"addresses,"},{"startTime":{"seconds":"191","nanos":900000000},"endTime":{"seconds":"192","nanos":900000000},"word":"perhaps"},{"startTime":{"seconds":"192","nanos":900000000},"endTime":{"seconds":"193","nanos":300000000},"word":"for"},{"startTime":{"seconds":"193","nanos":300000000},"endTime":{"seconds":"193","nanos":900000000},"word":"load"},{"startTime":{"seconds":"193","nanos":900000000},"endTime":{"seconds":"194","nanos":400000000},"word":"balancing"},{"startTime":{"seconds":"194","nanos":400000000},"endTime":{"seconds":"194","nanos":600000000},"word":"or"},{"startTime":{"seconds":"194","nanos":600000000},"endTime":{"seconds":"195"},"word":"scalability"},{"startTime":{"seconds":"195"},"endTime":{"seconds":"195","nanos":800000000},"word":"reasons."},{"startTime":{"seconds":"195","nanos":800000000},"endTime":{"seconds":"196","nanos":800000000},"word":"We"},{"startTime":{"seconds":"196","nanos":800000000},"endTime":{"seconds":"196","nanos":900000000},"word":"have"},{"startTime":{"seconds":"196","nanos":900000000},"endTime":{"seconds":"197","nanos":300000000},"word":"multiple"},{"startTime":{"seconds":"197","nanos":300000000},"endTime":{"seconds":"198"},"word":"replicas"},{"startTime":{"seconds":"198"},"endTime":{"seconds":"198","nanos":100000000},"word":"of"},{"startTime":{"seconds":"198","nanos":100000000},"endTime":{"seconds":"198","nanos":300000000},"word":"a"},{"startTime":{"seconds":"198","nanos":300000000},"endTime":{"seconds":"198","nanos":900000000},"word":"website."},{"startTime":{"seconds":"198","nanos":900000000},"endTime":{"seconds":"199","nanos":700000000},"word":"So"},{"startTime":{"seconds":"199","nanos":700000000},"endTime":{"seconds":"200","nanos":300000000},"word":"handling"},{"startTime":{"seconds":"200","nanos":300000000},"endTime":{"seconds":"200","nanos":500000000},"word":"load"},{"startTime":{"seconds":"200","nanos":500000000},"endTime":{"seconds":"200","nanos":900000000},"word":"balancing"},{"startTime":{"seconds":"200","nanos":900000000},"endTime":{"seconds":"201"},"word":"a"},{"startTime":{"seconds":"201"},"endTime":{"seconds":"201","nanos":500000000},"word":"reducing"},{"startTime":{"seconds":"201","nanos":500000000},"endTime":{"seconds":"201","nanos":800000000},"word":"late"},{"startTime":{"seconds":"201","nanos":800000000},"endTime":{"seconds":"201","nanos":900000000},"word":"and"},{"startTime":{"seconds":"201","nanos":900000000},"endTime":{"seconds":"202","nanos":100000000},"word":"see"},{"startTime":{"seconds":"202","nanos":100000000},"endTime":{"seconds":"202","nanos":800000000},"word":"if"},{"startTime":{"seconds":"202","nanos":800000000},"endTime":{"seconds":"203","nanos":100000000},"word":"perhaps"},{"startTime":{"seconds":"203","nanos":100000000},"endTime":{"seconds":"203","nanos":500000000},"word":"we"},{"startTime":{"seconds":"203","nanos":500000000},"endTime":{"seconds":"203","nanos":600000000},"word":"put"},{"startTime":{"seconds":"203","nanos":600000000},"endTime":{"seconds":"204","nanos":400000000},"word":"a"},{"startTime":{"seconds":"204","nanos":400000000},"endTime":{"seconds":"205"},"word":"server"},{"startTime":{"seconds":"205"},"endTime":{"seconds":"205","nanos":500000000},"word":"hosting"},{"startTime":{"seconds":"205","nanos":500000000},"endTime":{"seconds":"206"},"word":"CNN.com"},{"startTime":{"seconds":"206"},"endTime":{"seconds":"207","nanos":900000000},"word":"saying"},{"startTime":{"seconds":"207","nanos":900000000},"endTime":{"seconds":"208","nanos":200000000},"word":"different"},{"startTime":{"seconds":"208","nanos":200000000},"endTime":{"seconds":"208","nanos":800000000},"word":"country"},{"startTime":{"seconds":"208","nanos":800000000},"endTime":{"seconds":"209"},"word":"so"},{"startTime":{"seconds":"209"},"endTime":{"seconds":"209"},"word":"that"},{"startTime":{"seconds":"209"},"endTime":{"seconds":"209","nanos":300000000},"word":"there"},{"startTime":{"seconds":"209","nanos":300000000},"endTime":{"seconds":"209","nanos":400000000},"word":"is"},{"startTime":{"seconds":"209","nanos":400000000},"endTime":{"seconds":"209","nanos":600000000},"word":"always"},{"startTime":{"seconds":"209","nanos":600000000},"endTime":{"seconds":"209","nanos":900000000},"word":"one"},{"startTime":{"seconds":"209","nanos":900000000},"endTime":{"seconds":"210","nanos":200000000},"word":"close"},{"startTime":{"seconds":"210","nanos":200000000},"endTime":{"seconds":"210","nanos":500000000},"word":"by"},{"startTime":{"seconds":"210","nanos":500000000},"endTime":{"seconds":"210","nanos":800000000},"word":"to"},{"startTime":{"seconds":"210","nanos":800000000},"endTime":{"seconds":"211","nanos":700000000},"word":"people"},{"startTime":{"seconds":"211","nanos":700000000},"endTime":{"seconds":"212","nanos":500000000},"word":"likely"},{"startTime":{"seconds":"212","nanos":500000000},"endTime":{"seconds":"212","nanos":700000000},"word":"to"},{"startTime":{"seconds":"212","nanos":700000000},"endTime":{"seconds":"212","nanos":900000000},"word":"try"},{"startTime":{"seconds":"212","nanos":900000000},"endTime":{"seconds":"213"},"word":"to"},{"startTime":{"seconds":"213"},"endTime":{"seconds":"213","nanos":600000000},"word":"access"},{"startTime":{"seconds":"213","nanos":600000000},"endTime":{"seconds":"213","nanos":800000000},"word":"that"},{"startTime":{"seconds":"213","nanos":800000000},"endTime":{"seconds":"214","nanos":500000000},"word":"server."}]}]},{"alternatives":[{"transcript":" We could also do things like Taylor the content based on this based on the requesters location or identity, and we could have multiple names for the same address within this so that we could have a Leah says, and there may be good reasons to do that. So, ww.w, if that's prefixed in a domain name. I typically would correspond to a web server. But if you just access CNN.com, that probably also works and gets directed to the web server. Whereas CNN.com might, it doesn't have to direct to that web server.","confidence":0.9631819128990173,"words":[{"startTime":{"seconds":"215","nanos":300000000},"endTime":{"seconds":"216","nanos":100000000},"word":"We"},{"startTime":{"seconds":"216","nanos":100000000},"endTime":{"seconds":"216","nanos":300000000},"word":"could"},{"startTime":{"seconds":"216","nanos":300000000},"endTime":{"seconds":"216","nanos":500000000},"word":"also"},{"startTime":{"seconds":"216","nanos":500000000},"endTime":{"seconds":"216","nanos":700000000},"word":"do"},{"startTime":{"seconds":"216","nanos":700000000},"endTime":{"seconds":"217"},"word":"things"},{"startTime":{"seconds":"217"},"endTime":{"seconds":"217","nanos":100000000},"word":"like"},{"startTime":{"seconds":"217","nanos":100000000},"endTime":{"seconds":"217","nanos":500000000},"word":"Taylor"},{"startTime":{"seconds":"217","nanos":500000000},"endTime":{"seconds":"217","nanos":600000000},"word":"the"},{"startTime":{"seconds":"217","nanos":600000000},"endTime":{"seconds":"218","nanos":100000000},"word":"content"},{"startTime":{"seconds":"218","nanos":100000000},"endTime":{"seconds":"218","nanos":300000000},"word":"based"},{"startTime":{"seconds":"218","nanos":300000000},"endTime":{"seconds":"218","nanos":600000000},"word":"on"},{"startTime":{"seconds":"218","nanos":600000000},"endTime":{"seconds":"218","nanos":700000000},"word":"this"},{"startTime":{"seconds":"218","nanos":700000000},"endTime":{"seconds":"219","nanos":200000000},"word":"based"},{"startTime":{"seconds":"219","nanos":200000000},"endTime":{"seconds":"219","nanos":400000000},"word":"on"},{"startTime":{"seconds":"219","nanos":400000000},"endTime":{"seconds":"219","nanos":500000000},"word":"the"},{"startTime":{"seconds":"219","nanos":500000000},"endTime":{"seconds":"220","nanos":800000000},"word":"requesters"},{"startTime":{"seconds":"220","nanos":800000000},"endTime":{"seconds":"221","nanos":400000000},"word":"location"},{"startTime":{"seconds":"221","nanos":400000000},"endTime":{"seconds":"221","nanos":500000000},"word":"or"},{"startTime":{"seconds":"221","nanos":500000000},"endTime":{"seconds":"221","nanos":900000000},"word":"identity,"},{"startTime":{"seconds":"221","nanos":900000000},"endTime":{"seconds":"222","nanos":900000000},"word":"and"},{"startTime":{"seconds":"222","nanos":900000000},"endTime":{"seconds":"223","nanos":100000000},"word":"we"},{"startTime":{"seconds":"223","nanos":100000000},"endTime":{"seconds":"223","nanos":400000000},"word":"could"},{"startTime":{"seconds":"223","nanos":400000000},"endTime":{"seconds":"223","nanos":600000000},"word":"have"},{"startTime":{"seconds":"223","nanos":600000000},"endTime":{"seconds":"224","nanos":100000000},"word":"multiple"},{"startTime":{"seconds":"224","nanos":100000000},"endTime":{"seconds":"224","nanos":500000000},"word":"names"},{"startTime":{"seconds":"224","nanos":500000000},"endTime":{"seconds":"225"},"word":"for"},{"startTime":{"seconds":"225"},"endTime":{"seconds":"225","nanos":100000000},"word":"the"},{"startTime":{"seconds":"225","nanos":100000000},"endTime":{"seconds":"225","nanos":200000000},"word":"same"},{"startTime":{"seconds":"225","nanos":200000000},"endTime":{"seconds":"225","nanos":600000000},"word":"address"},{"startTime":{"seconds":"225","nanos":600000000},"endTime":{"seconds":"226","nanos":800000000},"word":"within"},{"startTime":{"seconds":"226","nanos":800000000},"endTime":{"seconds":"227"},"word":"this"},{"startTime":{"seconds":"227"},"endTime":{"seconds":"227","nanos":500000000},"word":"so"},{"startTime":{"seconds":"227","nanos":500000000},"endTime":{"seconds":"227","nanos":700000000},"word":"that"},{"startTime":{"seconds":"227","nanos":700000000},"endTime":{"seconds":"227","nanos":800000000},"word":"we"},{"startTime":{"seconds":"227","nanos":800000000},"endTime":{"seconds":"227","nanos":900000000},"word":"could"},{"startTime":{"seconds":"227","nanos":900000000},"endTime":{"seconds":"228"},"word":"have"},{"startTime":{"seconds":"228"},"endTime":{"seconds":"228","nanos":100000000},"word":"a"},{"startTime":{"seconds":"228","nanos":100000000},"endTime":{"seconds":"228","nanos":500000000},"word":"Leah"},{"startTime":{"seconds":"228","nanos":500000000},"endTime":{"seconds":"228","nanos":800000000},"word":"says,"},{"startTime":{"seconds":"228","nanos":800000000},"endTime":{"seconds":"229","nanos":100000000},"word":"and"},{"startTime":{"seconds":"229","nanos":100000000},"endTime":{"seconds":"229","nanos":200000000},"word":"there"},{"startTime":{"seconds":"229","nanos":200000000},"endTime":{"seconds":"229","nanos":300000000},"word":"may"},{"startTime":{"seconds":"229","nanos":300000000},"endTime":{"seconds":"229","nanos":400000000},"word":"be"},{"startTime":{"seconds":"229","nanos":400000000},"endTime":{"seconds":"229","nanos":600000000},"word":"good"},{"startTime":{"seconds":"229","nanos":600000000},"endTime":{"seconds":"229","nanos":700000000},"word":"reasons"},{"startTime":{"seconds":"229","nanos":700000000},"endTime":{"seconds":"230","nanos":300000000},"word":"to"},{"startTime":{"seconds":"230","nanos":300000000},"endTime":{"seconds":"230","nanos":500000000},"word":"do"},{"startTime":{"seconds":"230","nanos":500000000},"endTime":{"seconds":"230","nanos":700000000},"word":"that."},{"startTime":{"seconds":"230","nanos":700000000},"endTime":{"seconds":"231","nanos":400000000},"word":"So,"},{"startTime":{"seconds":"231","nanos":400000000},"endTime":{"seconds":"232","nanos":400000000},"word":"ww.w,"},{"startTime":{"seconds":"232","nanos":400000000},"endTime":{"seconds":"233","nanos":200000000},"word":"if"},{"startTime":{"seconds":"233","nanos":200000000},"endTime":{"seconds":"233","nanos":500000000},"word":"that's"},{"startTime":{"seconds":"233","nanos":500000000},"endTime":{"seconds":"234","nanos":200000000},"word":"prefixed"},{"startTime":{"seconds":"234","nanos":200000000},"endTime":{"seconds":"234","nanos":300000000},"word":"in"},{"startTime":{"seconds":"234","nanos":300000000},"endTime":{"seconds":"234","nanos":400000000},"word":"a"},{"startTime":{"seconds":"234","nanos":400000000},"endTime":{"seconds":"234","nanos":600000000},"word":"domain"},{"startTime":{"seconds":"234","nanos":600000000},"endTime":{"seconds":"234","nanos":900000000},"word":"name."},{"startTime":{"seconds":"234","nanos":900000000},"endTime":{"seconds":"235","nanos":600000000},"word":"I"},{"startTime":{"seconds":"235","nanos":600000000},"endTime":{"seconds":"236","nanos":100000000},"word":"typically"},{"startTime":{"seconds":"236","nanos":100000000},"endTime":{"seconds":"236","nanos":200000000},"word":"would"},{"startTime":{"seconds":"236","nanos":200000000},"endTime":{"seconds":"236","nanos":800000000},"word":"correspond"},{"startTime":{"seconds":"236","nanos":800000000},"endTime":{"seconds":"237"},"word":"to"},{"startTime":{"seconds":"237"},"endTime":{"seconds":"237"},"word":"a"},{"startTime":{"seconds":"237"},"endTime":{"seconds":"237","nanos":300000000},"word":"web"},{"startTime":{"seconds":"237","nanos":300000000},"endTime":{"seconds":"237","nanos":700000000},"word":"server."},{"startTime":{"seconds":"237","nanos":700000000},"endTime":{"seconds":"238","nanos":100000000},"word":"But"},{"startTime":{"seconds":"238","nanos":100000000},"endTime":{"seconds":"238","nanos":200000000},"word":"if"},{"startTime":{"seconds":"238","nanos":200000000},"endTime":{"seconds":"238","nanos":300000000},"word":"you"},{"startTime":{"seconds":"238","nanos":300000000},"endTime":{"seconds":"238","nanos":500000000},"word":"just"},{"startTime":{"seconds":"238","nanos":500000000},"endTime":{"seconds":"239"},"word":"access"},{"startTime":{"seconds":"239"},"endTime":{"seconds":"239","nanos":400000000},"word":"CNN.com,"},{"startTime":{"seconds":"239","nanos":400000000},"endTime":{"seconds":"239","nanos":900000000},"word":"that"},{"startTime":{"seconds":"239","nanos":900000000},"endTime":{"seconds":"240","nanos":300000000},"word":"probably"},{"startTime":{"seconds":"240","nanos":300000000},"endTime":{"seconds":"240","nanos":600000000},"word":"also"},{"startTime":{"seconds":"240","nanos":600000000},"endTime":{"seconds":"241","nanos":100000000},"word":"works"},{"startTime":{"seconds":"241","nanos":100000000},"endTime":{"seconds":"241","nanos":400000000},"word":"and"},{"startTime":{"seconds":"241","nanos":400000000},"endTime":{"seconds":"241","nanos":500000000},"word":"gets"},{"startTime":{"seconds":"241","nanos":500000000},"endTime":{"seconds":"242","nanos":100000000},"word":"directed"},{"startTime":{"seconds":"242","nanos":100000000},"endTime":{"seconds":"242","nanos":700000000},"word":"to"},{"startTime":{"seconds":"242","nanos":700000000},"endTime":{"seconds":"242","nanos":800000000},"word":"the"},{"startTime":{"seconds":"242","nanos":800000000},"endTime":{"seconds":"243"},"word":"web"},{"startTime":{"seconds":"243"},"endTime":{"seconds":"243","nanos":300000000},"word":"server."},{"startTime":{"seconds":"243","nanos":300000000},"endTime":{"seconds":"244"},"word":"Whereas"},{"startTime":{"seconds":"244"},"endTime":{"seconds":"244","nanos":700000000},"word":"CNN.com"},{"startTime":{"seconds":"244","nanos":700000000},"endTime":{"seconds":"245","nanos":500000000},"word":"might,"},{"startTime":{"seconds":"245","nanos":500000000},"endTime":{"seconds":"247","nanos":300000000},"word":"it"},{"startTime":{"seconds":"247","nanos":300000000},"endTime":{"seconds":"247","nanos":800000000},"word":"doesn't"},{"startTime":{"seconds":"247","nanos":800000000},"endTime":{"seconds":"248"},"word":"have"},{"startTime":{"seconds":"248"},"endTime":{"seconds":"248","nanos":200000000},"word":"to"},{"startTime":{"seconds":"248","nanos":200000000},"endTime":{"seconds":"248","nanos":600000000},"word":"direct"},{"startTime":{"seconds":"248","nanos":600000000},"endTime":{"seconds":"248","nanos":800000000},"word":"to"},{"startTime":{"seconds":"248","nanos":800000000},"endTime":{"seconds":"249"},"word":"that"},{"startTime":{"seconds":"249"},"endTime":{"seconds":"249","nanos":800000000},"word":"web"},{"startTime":{"seconds":"249","nanos":800000000},"endTime":{"seconds":"250","nanos":200000000},"word":"server."}]}]},{"alternatives":[{"transcript":" So, how do we, how does this work? Roughly, how does this mapping between names and addresses work? So, originally, this was done in a host file. I'm working with a flat namespace. Typically under Unix should be in / at see, such hosts and then an organization. One of the first organizations on the internet in the web, SRI in Menlo Park. We keep a Master Copy. So then others would need to download this file regularly, but this isn't going to scale, right? If there are a lot of lookups and if one organization was keeping track of this, it could overload that server and it would lead to a single point of failure. So this will motivate how DNS works and why we need a distributed and hierarchical collection of servers. So that this would scale up.","confidence":0.9823693633079529,"words":[{"startTime":{"seconds":"250","nanos":900000000},"endTime":{"seconds":"254","nanos":200000000},"word":"So,"},{"startTime":{"seconds":"254","nanos":200000000},"endTime":{"seconds":"255"},"word":"how"},{"startTime":{"seconds":"255"},"endTime":{"seconds":"255","nanos":100000000},"word":"do"},{"startTime":{"seconds":"255","nanos":100000000},"endTime":{"seconds":"255","nanos":100000000},"word":"we,"},{"startTime":{"seconds":"255","nanos":100000000},"endTime":{"seconds":"255","nanos":700000000},"word":"how"},{"startTime":{"seconds":"255","nanos":700000000},"endTime":{"seconds":"255","nanos":900000000},"word":"does"},{"startTime":{"seconds":"255","nanos":900000000},"endTime":{"seconds":"256"},"word":"this"},{"startTime":{"seconds":"256"},"endTime":{"seconds":"256","nanos":300000000},"word":"work?"},{"startTime":{"seconds":"256","nanos":300000000},"endTime":{"seconds":"256","nanos":600000000},"word":"Roughly,"},{"startTime":{"seconds":"256","nanos":600000000},"endTime":{"seconds":"257","nanos":500000000},"word":"how"},{"startTime":{"seconds":"257","nanos":500000000},"endTime":{"seconds":"257","nanos":700000000},"word":"does"},{"startTime":{"seconds":"257","nanos":700000000},"endTime":{"seconds":"257","nanos":800000000},"word":"this"},{"startTime":{"seconds":"257","nanos":800000000},"endTime":{"seconds":"258","nanos":200000000},"word":"mapping"},{"startTime":{"seconds":"258","nanos":200000000},"endTime":{"seconds":"258","nanos":700000000},"word":"between"},{"startTime":{"seconds":"258","nanos":700000000},"endTime":{"seconds":"259"},"word":"names"},{"startTime":{"seconds":"259"},"endTime":{"seconds":"259","nanos":100000000},"word":"and"},{"startTime":{"seconds":"259","nanos":100000000},"endTime":{"seconds":"259","nanos":500000000},"word":"addresses"},{"startTime":{"seconds":"259","nanos":500000000},"endTime":{"seconds":"259","nanos":900000000},"word":"work?"},{"startTime":{"seconds":"259","nanos":900000000},"endTime":{"seconds":"261"},"word":"So,"},{"startTime":{"seconds":"261"},"endTime":{"seconds":"261","nanos":600000000},"word":"originally,"},{"startTime":{"seconds":"261","nanos":600000000},"endTime":{"seconds":"261","nanos":800000000},"word":"this"},{"startTime":{"seconds":"261","nanos":800000000},"endTime":{"seconds":"262"},"word":"was"},{"startTime":{"seconds":"262"},"endTime":{"seconds":"262","nanos":300000000},"word":"done"},{"startTime":{"seconds":"262","nanos":300000000},"endTime":{"seconds":"262","nanos":400000000},"word":"in"},{"startTime":{"seconds":"262","nanos":400000000},"endTime":{"seconds":"262","nanos":500000000},"word":"a"},{"startTime":{"seconds":"262","nanos":500000000},"endTime":{"seconds":"263","nanos":500000000},"word":"host"},{"startTime":{"seconds":"263","nanos":500000000},"endTime":{"seconds":"263","nanos":700000000},"word":"file."},{"startTime":{"seconds":"263","nanos":700000000},"endTime":{"seconds":"264","nanos":800000000},"word":"I'm"},{"startTime":{"seconds":"264","nanos":800000000},"endTime":{"seconds":"265","nanos":100000000},"word":"working"},{"startTime":{"seconds":"265","nanos":100000000},"endTime":{"seconds":"265","nanos":200000000},"word":"with"},{"startTime":{"seconds":"265","nanos":200000000},"endTime":{"seconds":"265","nanos":300000000},"word":"a"},{"startTime":{"seconds":"265","nanos":300000000},"endTime":{"seconds":"265","nanos":700000000},"word":"flat"},{"startTime":{"seconds":"265","nanos":700000000},"endTime":{"seconds":"266","nanos":400000000},"word":"namespace."},{"startTime":{"seconds":"266","nanos":400000000},"endTime":{"seconds":"267","nanos":800000000},"word":"Typically"},{"startTime":{"seconds":"267","nanos":800000000},"endTime":{"seconds":"269","nanos":400000000},"word":"under"},{"startTime":{"seconds":"269","nanos":400000000},"endTime":{"seconds":"269","nanos":800000000},"word":"Unix"},{"startTime":{"seconds":"269","nanos":800000000},"endTime":{"seconds":"270"},"word":"should"},{"startTime":{"seconds":"270"},"endTime":{"seconds":"270","nanos":100000000},"word":"be"},{"startTime":{"seconds":"270","nanos":100000000},"endTime":{"seconds":"270","nanos":300000000},"word":"in"},{"startTime":{"seconds":"270","nanos":300000000},"endTime":{"seconds":"270","nanos":700000000},"word":"/"},{"startTime":{"seconds":"270","nanos":700000000},"endTime":{"seconds":"271"},"word":"at"},{"startTime":{"seconds":"271"},"endTime":{"seconds":"271","nanos":100000000},"word":"see,"},{"startTime":{"seconds":"271","nanos":100000000},"endTime":{"seconds":"271","nanos":400000000},"word":"such"},{"startTime":{"seconds":"271","nanos":400000000},"endTime":{"seconds":"271","nanos":900000000},"word":"hosts"},{"startTime":{"seconds":"271","nanos":900000000},"endTime":{"seconds":"272","nanos":900000000},"word":"and"},{"startTime":{"seconds":"272","nanos":900000000},"endTime":{"seconds":"273","nanos":200000000},"word":"then"},{"startTime":{"seconds":"273","nanos":200000000},"endTime":{"seconds":"273","nanos":300000000},"word":"an"},{"startTime":{"seconds":"273","nanos":300000000},"endTime":{"seconds":"274","nanos":300000000},"word":"organization."},{"startTime":{"seconds":"274","nanos":300000000},"endTime":{"seconds":"274","nanos":500000000},"word":"One"},{"startTime":{"seconds":"274","nanos":500000000},"endTime":{"seconds":"274","nanos":600000000},"word":"of"},{"startTime":{"seconds":"274","nanos":600000000},"endTime":{"seconds":"274","nanos":600000000},"word":"the"},{"startTime":{"seconds":"274","nanos":600000000},"endTime":{"seconds":"274","nanos":900000000},"word":"first"},{"startTime":{"seconds":"274","nanos":900000000},"endTime":{"seconds":"275","nanos":600000000},"word":"organizations"},{"startTime":{"seconds":"275","nanos":600000000},"endTime":{"seconds":"275","nanos":700000000},"word":"on"},{"startTime":{"seconds":"275","nanos":700000000},"endTime":{"seconds":"275","nanos":800000000},"word":"the"},{"startTime":{"seconds":"275","nanos":800000000},"endTime":{"seconds":"276","nanos":200000000},"word":"internet"},{"startTime":{"seconds":"276","nanos":200000000},"endTime":{"seconds":"276","nanos":300000000},"word":"in"},{"startTime":{"seconds":"276","nanos":300000000},"endTime":{"seconds":"276","nanos":400000000},"word":"the"},{"startTime":{"seconds":"276","nanos":400000000},"endTime":{"seconds":"276","nanos":700000000},"word":"web,"},{"startTime":{"seconds":"276","nanos":700000000},"endTime":{"seconds":"277","nanos":600000000},"word":"SRI"},{"startTime":{"seconds":"277","nanos":600000000},"endTime":{"seconds":"277","nanos":800000000},"word":"in"},{"startTime":{"seconds":"277","nanos":800000000},"endTime":{"seconds":"278","nanos":100000000},"word":"Menlo"},{"startTime":{"seconds":"278","nanos":100000000},"endTime":{"seconds":"278","nanos":500000000},"word":"Park."},{"startTime":{"seconds":"278","nanos":500000000},"endTime":{"seconds":"278","nanos":600000000},"word":"We"},{"startTime":{"seconds":"278","nanos":600000000},"endTime":{"seconds":"278","nanos":800000000},"word":"keep"},{"startTime":{"seconds":"278","nanos":800000000},"endTime":{"seconds":"278","nanos":900000000},"word":"a"},{"startTime":{"seconds":"278","nanos":900000000},"endTime":{"seconds":"279","nanos":400000000},"word":"Master"},{"startTime":{"seconds":"279","nanos":400000000},"endTime":{"seconds":"279","nanos":600000000},"word":"Copy."},{"startTime":{"seconds":"279","nanos":600000000},"endTime":{"seconds":"280","nanos":400000000},"word":"So"},{"startTime":{"seconds":"280","nanos":400000000},"endTime":{"seconds":"280","nanos":600000000},"word":"then"},{"startTime":{"seconds":"280","nanos":600000000},"endTime":{"seconds":"280","nanos":900000000},"word":"others"},{"startTime":{"seconds":"280","nanos":900000000},"endTime":{"seconds":"281"},"word":"would"},{"startTime":{"seconds":"281"},"endTime":{"seconds":"281","nanos":200000000},"word":"need"},{"startTime":{"seconds":"281","nanos":200000000},"endTime":{"seconds":"281","nanos":200000000},"word":"to"},{"startTime":{"seconds":"281","nanos":200000000},"endTime":{"seconds":"281","nanos":500000000},"word":"download"},{"startTime":{"seconds":"281","nanos":500000000},"endTime":{"seconds":"281","nanos":800000000},"word":"this"},{"startTime":{"seconds":"281","nanos":800000000},"endTime":{"seconds":"282","nanos":100000000},"word":"file"},{"startTime":{"seconds":"282","nanos":100000000},"endTime":{"seconds":"282","nanos":800000000},"word":"regularly,"},{"startTime":{"seconds":"282","nanos":800000000},"endTime":{"seconds":"283","nanos":100000000},"word":"but"},{"startTime":{"seconds":"283","nanos":100000000},"endTime":{"seconds":"283","nanos":300000000},"word":"this"},{"startTime":{"seconds":"283","nanos":300000000},"endTime":{"seconds":"283","nanos":500000000},"word":"isn't"},{"startTime":{"seconds":"283","nanos":500000000},"endTime":{"seconds":"283","nanos":700000000},"word":"going"},{"startTime":{"seconds":"283","nanos":700000000},"endTime":{"seconds":"283","nanos":800000000},"word":"to"},{"startTime":{"seconds":"283","nanos":800000000},"endTime":{"seconds":"284","nanos":200000000},"word":"scale,"},{"startTime":{"seconds":"284","nanos":200000000},"endTime":{"seconds":"284","nanos":500000000},"word":"right?"},{"startTime":{"seconds":"284","nanos":500000000},"endTime":{"seconds":"285","nanos":500000000},"word":"If"},{"startTime":{"seconds":"285","nanos":500000000},"endTime":{"seconds":"285","nanos":600000000},"word":"there"},{"startTime":{"seconds":"285","nanos":600000000},"endTime":{"seconds":"285","nanos":700000000},"word":"are"},{"startTime":{"seconds":"285","nanos":700000000},"endTime":{"seconds":"285","nanos":700000000},"word":"a"},{"startTime":{"seconds":"285","nanos":700000000},"endTime":{"seconds":"285","nanos":900000000},"word":"lot"},{"startTime":{"seconds":"285","nanos":900000000},"endTime":{"seconds":"285","nanos":900000000},"word":"of"},{"startTime":{"seconds":"285","nanos":900000000},"endTime":{"seconds":"286","nanos":600000000},"word":"lookups"},{"startTime":{"seconds":"286","nanos":600000000},"endTime":{"seconds":"287","nanos":300000000},"word":"and"},{"startTime":{"seconds":"287","nanos":300000000},"endTime":{"seconds":"287","nanos":500000000},"word":"if"},{"startTime":{"seconds":"287","nanos":500000000},"endTime":{"seconds":"287","nanos":900000000},"word":"one"},{"startTime":{"seconds":"287","nanos":900000000},"endTime":{"seconds":"288","nanos":600000000},"word":"organization"},{"startTime":{"seconds":"288","nanos":600000000},"endTime":{"seconds":"288","nanos":800000000},"word":"was"},{"startTime":{"seconds":"288","nanos":800000000},"endTime":{"seconds":"289","nanos":100000000},"word":"keeping"},{"startTime":{"seconds":"289","nanos":100000000},"endTime":{"seconds":"289","nanos":300000000},"word":"track"},{"startTime":{"seconds":"289","nanos":300000000},"endTime":{"seconds":"289","nanos":400000000},"word":"of"},{"startTime":{"seconds":"289","nanos":400000000},"endTime":{"seconds":"289","nanos":600000000},"word":"this,"},{"startTime":{"seconds":"289","nanos":600000000},"endTime":{"seconds":"291","nanos":800000000},"word":"it"},{"startTime":{"seconds":"291","nanos":800000000},"endTime":{"seconds":"292"},"word":"could"},{"startTime":{"seconds":"292"},"endTime":{"seconds":"293","nanos":100000000},"word":"overload"},{"startTime":{"seconds":"293","nanos":100000000},"endTime":{"seconds":"293","nanos":400000000},"word":"that"},{"startTime":{"seconds":"293","nanos":400000000},"endTime":{"seconds":"293","nanos":800000000},"word":"server"},{"startTime":{"seconds":"293","nanos":800000000},"endTime":{"seconds":"294","nanos":500000000},"word":"and"},{"startTime":{"seconds":"294","nanos":500000000},"endTime":{"seconds":"294","nanos":600000000},"word":"it"},{"startTime":{"seconds":"294","nanos":600000000},"endTime":{"seconds":"294","nanos":700000000},"word":"would"},{"startTime":{"seconds":"294","nanos":700000000},"endTime":{"seconds":"294","nanos":900000000},"word":"lead"},{"startTime":{"seconds":"294","nanos":900000000},"endTime":{"seconds":"295"},"word":"to"},{"startTime":{"seconds":"295"},"endTime":{"seconds":"295","nanos":100000000},"word":"a"},{"startTime":{"seconds":"295","nanos":100000000},"endTime":{"seconds":"295","nanos":500000000},"word":"single"},{"startTime":{"seconds":"295","nanos":500000000},"endTime":{"seconds":"295","nanos":600000000},"word":"point"},{"startTime":{"seconds":"295","nanos":600000000},"endTime":{"seconds":"295","nanos":700000000},"word":"of"},{"startTime":{"seconds":"295","nanos":700000000},"endTime":{"seconds":"295","nanos":800000000},"word":"failure."},{"startTime":{"seconds":"295","nanos":800000000},"endTime":{"seconds":"297"},"word":"So"},{"startTime":{"seconds":"297"},"endTime":{"seconds":"297","nanos":200000000},"word":"this"},{"startTime":{"seconds":"297","nanos":200000000},"endTime":{"seconds":"297","nanos":400000000},"word":"will"},{"startTime":{"seconds":"297","nanos":400000000},"endTime":{"seconds":"297","nanos":600000000},"word":"motivate"},{"startTime":{"seconds":"297","nanos":600000000},"endTime":{"seconds":"298","nanos":500000000},"word":"how"},{"startTime":{"seconds":"298","nanos":500000000},"endTime":{"seconds":"298","nanos":900000000},"word":"DNS"},{"startTime":{"seconds":"298","nanos":900000000},"endTime":{"seconds":"299","nanos":600000000},"word":"works"},{"startTime":{"seconds":"299","nanos":600000000},"endTime":{"seconds":"299","nanos":900000000},"word":"and"},{"startTime":{"seconds":"299","nanos":900000000},"endTime":{"seconds":"300","nanos":100000000},"word":"why"},{"startTime":{"seconds":"300","nanos":100000000},"endTime":{"seconds":"300","nanos":500000000},"word":"we"},{"startTime":{"seconds":"300","nanos":500000000},"endTime":{"seconds":"300","nanos":700000000},"word":"need"},{"startTime":{"seconds":"300","nanos":700000000},"endTime":{"seconds":"300","nanos":800000000},"word":"a"},{"startTime":{"seconds":"300","nanos":800000000},"endTime":{"seconds":"301","nanos":500000000},"word":"distributed"},{"startTime":{"seconds":"301","nanos":500000000},"endTime":{"seconds":"301","nanos":700000000},"word":"and"},{"startTime":{"seconds":"301","nanos":700000000},"endTime":{"seconds":"302","nanos":200000000},"word":"hierarchical"},{"startTime":{"seconds":"302","nanos":200000000},"endTime":{"seconds":"303","nanos":100000000},"word":"collection"},{"startTime":{"seconds":"303","nanos":100000000},"endTime":{"seconds":"303","nanos":200000000},"word":"of"},{"startTime":{"seconds":"303","nanos":200000000},"endTime":{"seconds":"303","nanos":700000000},"word":"servers."},{"startTime":{"seconds":"303","nanos":700000000},"endTime":{"seconds":"304","nanos":700000000},"word":"So"},{"startTime":{"seconds":"304","nanos":700000000},"endTime":{"seconds":"304","nanos":900000000},"word":"that"},{"startTime":{"seconds":"304","nanos":900000000},"endTime":{"seconds":"305","nanos":100000000},"word":"this"},{"startTime":{"seconds":"305","nanos":100000000},"endTime":{"seconds":"305","nanos":300000000},"word":"would"},{"startTime":{"seconds":"305","nanos":300000000},"endTime":{"seconds":"305","nanos":700000000},"word":"scale"},{"startTime":{"seconds":"305","nanos":700000000},"endTime":{"seconds":"305","nanos":900000000},"word":"up."}]}]}],"totalBilledTime":{"seconds":"315"}}